mpdbg/__init__.py
mpdbg/__main__.py
mpdbg/image.py
mpdbg/main.py
mpdbg/mpd_utils.py
mpdbg/mpdbg.py
mpdbg/shell.py
mpdbg/wallpaper.py
mpdbg-0.1.3.dist-info/COPYING
mpdbg-0.1.3.dist-info/METADATA
mpdbg-0.1.3.dist-info/WHEEL
mpdbg-0.1.3.dist-info/entry_points.txt
mpdbg-0.1.3.dist-info/RECORD
