Metadata-Version: 2.1
Name: mpdbg
Version: 0.1.3
Summary: Display MPD's current song's cover art on top of wallpaper
Home-page: https://git.dragonwit.dev/dragonwit/mpdbg-py
License: GPL-3.0-only
Author: dragonwit
Author-email: dragonwit@dragonwit.dev
Requires-Python: >=3.7.2
Classifier: License :: OSI Approved :: GNU General Public License v3 (GPLv3)
Classifier: Programming Language :: Python :: 3
Classifier: Programming Language :: Python :: 3.8
Classifier: Programming Language :: Python :: 3.9
Classifier: Programming Language :: Python :: 3.10
Classifier: Programming Language :: Python :: 3.11
Requires-Dist: click (>=8.1.3,<9.0.0)
Requires-Dist: mslex (>=1.1.0,<2.0.0)
Requires-Dist: pillow (>=9.5.0,<10.0.0)
Requires-Dist: python-mpd2 (>=3.1.0,<4.0.0)
Project-URL: Repository, https://git.dragonwit.dev/dragonwit/mpdbg-py
